dicttowddx/__init__.py
dicttowddx/main.py
dicttowddx-0.2.0.dist-info/LICENSE
dicttowddx-0.2.0.dist-info/METADATA
dicttowddx-0.2.0.dist-info/WHEEL
dicttowddx-0.2.0.dist-info/top_level.txt
dicttowddx-0.2.0.dist-info/RECORD
