Metadata-Version: 2.1
Name: dicttowddx
Version: 0.2.0
Summary: Utility lib to convert python dictionaries to valid WDDX data exchange format
Home-page: https://github.com/dotman14/dicttowddx
Author: Oyedotun Oyesanmi
Author-email: dotunoyesanmi@gmail.com
License: MIT
Keywords: python,wddx,data exchange
Classifier: Intended Audience :: Developers
Classifier: License :: OSI Approved :: MIT License
Classifier: Programming Language :: Python :: 3
Classifier: Operating System :: OS Independent
Requires-Python: >=3.8.0
License-File: LICENSE
Requires-Dist: yattag
Provides-Extra: dev
Requires-Dist: pytest-cov >=4.1.0 ; extra == 'dev'
